<?xml version="1.0" encoding="UTF-8"?>
<AnyConnectPreferences>
<DefaultUser></DefaultUser>
<DefaultSecondUser></DefaultSecondUser>
<ClientCertificateThumbprint></ClientCertificateThumbprint>
<MultipleClientCertificateThumbprints></MultipleClientCertificateThumbprints>
<ServerCertificateThumbprint></ServerCertificateThumbprint>
<DefaultHostName>andsim-f01-qbpqntgmpc.dynamic-m.com:4443</DefaultHostName>
<DefaultHostAddress>122.56.100.139:4443</DefaultHostAddress>
<DefaultGroup></DefaultGroup>
<ProxyHost></ProxyHost>
<ProxyPort></ProxyPort>
<SDITokenType>none</SDITokenType>
<ControllablePreferences>
<LocalLanAccess>true</LocalLanAccess></ControllablePreferences>
</AnyConnectPreferences>
